<?xml version="1.0" encoding="UTF-8"?>
<sv:node xmlns:sv="http://www.jcp.org/jcr/sv/1.0" xmlns:xsi="http://www.w3.org/2001/XMLSchema-instance" sv:name="commands">
  <sv:property sv:name="jcr:primaryType" sv:type="Name">
    <sv:value>mgnl:content</sv:value>
  </sv:property>
  <sv:node sv:name="subscriptions">
    <sv:property sv:name="jcr:primaryType" sv:type="Name">
      <sv:value>mgnl:content</sv:value>
    </sv:property>
    <sv:node sv:name="addSubscriber">
      <sv:property sv:name="jcr:primaryType" sv:type="Name">
        <sv:value>mgnl:contentNode</sv:value>
      </sv:property>
      <sv:property sv:name="class" sv:type="String">
        <sv:value>info.magnolia.services.subscriptiontools.commands.AddSubscriberCommand</sv:value>
      </sv:property>
    </sv:node>
    <sv:node sv:name="activateSubscriber">
      <sv:property sv:name="jcr:primaryType" sv:type="Name">
        <sv:value>mgnl:contentNode</sv:value>
      </sv:property>
      <sv:property sv:name="class" sv:type="String">
        <sv:value>info.magnolia.services.subscriptiontools.commands.ActivateSubscriberCommand</sv:value>
      </sv:property>
    </sv:node>
    <sv:node sv:name="deactivateSubscriber">
      <sv:property sv:name="jcr:primaryType" sv:type="Name">
        <sv:value>mgnl:contentNode</sv:value>
      </sv:property>
      <sv:property sv:name="class" sv:type="String">
        <sv:value>info.magnolia.services.subscriptiontools.commands.DeactivateSubscriberCommand</sv:value>
      </sv:property>
    </sv:node>
    <sv:node sv:name="removeSubscriber">
      <sv:property sv:name="jcr:primaryType" sv:type="Name">
        <sv:value>mgnl:contentNode</sv:value>
      </sv:property>
      <sv:property sv:name="class" sv:type="String">
        <sv:value>info.magnolia.services.subscriptiontools.commands.RemoveSubscriberCommand</sv:value>
      </sv:property>
    </sv:node>
    <sv:node sv:name="getPublicKey">
      <sv:property sv:name="jcr:primaryType" sv:type="Name">
        <sv:value>mgnl:contentNode</sv:value>
      </sv:property>
      <sv:property sv:name="class" sv:type="String">
        <sv:value>info.magnolia.services.subscriptiontools.commands.GetPublicKeyCommand</sv:value>
      </sv:property>
    </sv:node>
  </sv:node>
</sv:node>

